django_freshdesk-1.1.1.dist-info/DESCRIPTION.rst
django_freshdesk-1.1.1.dist-info/LICENSE.txt
django_freshdesk-1.1.1.dist-info/METADATA
django_freshdesk-1.1.1.dist-info/RECORD
django_freshdesk-1.1.1.dist-info/WHEEL
django_freshdesk-1.1.1.dist-info/metadata.json
django_freshdesk-1.1.1.dist-info/top_level.txt
freshdesk/__init__.py
freshdesk/models.py
freshdesk/tests.py
freshdesk/urls.py
freshdesk/views.py
