Metadata-Version: 2.0
Name: django-freshdesk
Version: 1.1.1
Summary: Single Sign-On functionallity between Django and Freshdesk
Home-page: https://github.com/ThatGreenSpace/django-freshdesk/
Author: That Green Space Pte Ltd
Author-email: engineering@thatgreenspace.com.sg
License: BSD
Platform: OS Independent
Classifier: Development Status :: 4 - Beta
Classifier: Environment :: Web Environment
Classifier: Intended Audience :: Developers
Classifier: License :: OSI Approved :: BSD License
Classifier: Operating System :: OS Independent
Classifier: Programming Language :: Python
Classifier: Programming Language :: Python :: 2
Classifier: Programming Language :: Python :: 2.7
Classifier: Programming Language :: Python :: 3
Classifier: Programming Language :: Python :: 3.4
Classifier: Programming Language :: Python :: 3.5
Classifier: Programming Language :: Python :: 3.6
Classifier: Framework :: Django
Classifier: Topic :: Internet :: WWW/HTTP :: Dynamic Content
Requires-Dist: Django (>1.7,<1.11)
